geode_gem/__init__.py
geode_gem/__main__.py
geode_gem/data/__init__.py
geode_gem/data/config/__init__.py
geode_gem/data/config/consoles.conf
geode_gem/data/config/databases.conf
geode_gem/data/config/emulators.conf
geode_gem/data/config/gem.conf
geode_gem/data/config/log.conf
geode_gem/data/config/metadata.conf
geode_gem/data/config/shortcuts.conf
geode_gem/data/desktop/__init__.py
geode_gem/data/desktop/gem.desktop
geode_gem/data/desktop/gem.svg
geode_gem/data/docs/LICENSE.emulators.md
geode_gem/data/i18n/en/LC_MESSAGES/geode_gem.mo
geode_gem/data/i18n/es/LC_MESSAGES/geode_gem.mo
geode_gem/data/i18n/fr/LC_MESSAGES/geode_gem.mo
geode_gem/data/icons/__init__.py
geode_gem/data/icons/amstrad-gx4000.png
geode_gem/data/icons/atari-2600.png
geode_gem/data/icons/atari-400.png
geode_gem/data/icons/atari-5200.png
geode_gem/data/icons/atari-600xl.png
geode_gem/data/icons/atari-7800.png
geode_gem/data/icons/atari-800xl.png
geode_gem/data/icons/atari-jaguar.png
geode_gem/data/icons/atari-lynx.png
geode_gem/data/icons/bandai-wonderswan.png
geode_gem/data/icons/bandai-wonderswancolor.png
geode_gem/data/icons/coleco-colecovision.png
geode_gem/data/icons/commodore-128.png
geode_gem/data/icons/commodore-64.png
geode_gem/data/icons/emerson-arcadia2001.png
geode_gem/data/icons/mattel-intellivision.png
geode_gem/data/icons/microsoft-xbox.png
geode_gem/data/icons/microsoft-xbox360.png
geode_gem/data/icons/nec-pcengine.png
geode_gem/data/icons/nec-pcfx.png
geode_gem/data/icons/nec-turboduo.png
geode_gem/data/icons/nec-turbografx-cd.png
geode_gem/data/icons/nec-turbografx.png
geode_gem/data/icons/nintendo-3ds.png
geode_gem/data/icons/nintendo-ds.png
geode_gem/data/icons/nintendo-famicom.png
geode_gem/data/icons/nintendo-gameboy.png
geode_gem/data/icons/nintendo-gameboyadvance.png
geode_gem/data/icons/nintendo-gameboycolor.png
geode_gem/data/icons/nintendo-gamecube.png
geode_gem/data/icons/nintendo-n64.png
geode_gem/data/icons/nintendo-nes.png
geode_gem/data/icons/nintendo-snes.png
Geode_GEM-0.12.0.dist-info/LICENSE
Geode_GEM-0.12.0.dist-info/METADATA
Geode_GEM-0.12.0.dist-info/WHEEL
Geode_GEM-0.12.0.dist-info/entry_points.txt
Geode_GEM-0.12.0.dist-info/top_level.txt
Geode_GEM-0.12.0.dist-info/RECORD
