Metadata-Version: 2.1
Name: Geode-GEM
Version: 0.12.0
Summary: Geode-GEM is an interface to manage emulators and games
Home-page: https://gem.tuxfamily.org
Author: PacMiam
Author-email: pacmiam@tuxfamily.org
License: UNKNOWN
Project-URL: Archives, https://download.tuxfamily.org/gem/releases
Project-URL: Source, https://framagit.org/geode/gem
Project-URL: Tracker, https://framagit.org/geode/gem/issues
Keywords: gtk+ emulators games
Platform: UNKNOWN
Classifier: Development Status :: 5 - Production/Stable
Classifier: Environment :: X11 Applications :: GTK
Classifier: Intended Audience :: End Users/Desktop
Classifier: License :: OSI Approved :: GNU General Public License v3 or later (GPLv3+)
Classifier: Natural Language :: French
Classifier: Operating System :: POSIX :: Linux
Classifier: Programming Language :: Python :: 3.8
Classifier: Programming Language :: Python :: 3.9
Classifier: Programming Language :: Python :: 3 :: Only
Classifier: Topic :: Games/Entertainment
Classifier: Topic :: Utilities
Requires-Python: ~= 3.8
License-File: LICENSE
Requires-Dist: PyGobject (~=3.32)
Requires-Dist: pyxdg (~=0.26)
Provides-Extra: dev
Requires-Dist: flake8 ; extra == 'dev'
Requires-Dist: pytest ; extra == 'dev'
Requires-Dist: tox ; extra == 'dev'
